{
  "$schema": "http://json-schema.org/draft-07/schema#",
  "version": "0.1.0",
  "description": "Directed tag relationship edges for graph traversal",
  "relation_types": [
    {
      "type": "symptom_of",
      "description": "Source tag is a symptom of target tag"
    },
    {
      "type": "often_caused_by",
      "description": "Source issue is often caused by target"
    },
    { "type": "related", "description": "Tags are conceptually related" },
    { "type": "subtopic", "description": "Source is a subtopic of target" },
    {
      "type": "replaces",
      "description": "Source tag replaces deprecated target"
    }
  ],
  "edges": [
    {
      "source": "symptom.lumen_noise",
      "target": "rendering.lumen",
      "relation": "symptom_of",
      "weight": 0.95
    },
    {
      "source": "build.exitcode_25",
      "target": "build.packaging",
      "relation": "symptom_of",
      "weight": 0.9
    },
    {
      "source": "build.exitcode_6",
      "target": "build.packaging",
      "relation": "symptom_of",
      "weight": 0.9
    },
    {
      "source": "blueprint.accessed_none",
      "target": "scripting.blueprint",
      "relation": "symptom_of",
      "weight": 0.95
    },
    {
      "source": "blueprint.infinite_loop",
      "target": "scripting.blueprint",
      "relation": "symptom_of",
      "weight": 0.85
    },
    {
      "source": "crash.d3d_device_lost",
      "target": "rendering.lumen",
      "relation": "often_caused_by",
      "weight": 0.6
    },
    {
      "source": "crash.d3d_device_lost",
      "target": "rendering.nanite",
      "relation": "often_caused_by",
      "weight": 0.5
    },
    {
      "source": "crash.d3d_device_lost",
      "target": "rendering.raytracing",
      "relation": "often_caused_by",
      "weight": 0.7
    },
    {
      "source": "crash.access_violation",
      "target": "blueprint.accessed_none",
      "relation": "often_caused_by",
      "weight": 0.4
    },
    {
      "source": "crash.access_violation",
      "target": "scripting.cpp",
      "relation": "often_caused_by",
      "weight": 0.6
    },
    {
      "source": "scripting.blueprint",
      "target": "scripting.cpp",
      "relation": "related",
      "weight": 0.8
    },
    {
      "source": "scripting.anim_blueprint",
      "target": "scripting.blueprint",
      "relation": "subtopic",
      "weight": 0.9
    },
    {
      "source": "scripting.anim_blueprint",
      "target": "animation.general",
      "relation": "related",
      "weight": 0.85
    },
    {
      "source": "rendering.lumen",
      "target": "rendering.nanite",
      "relation": "related",
      "weight": 0.85
    },
    {
      "source": "rendering.lumen",
      "target": "rendering.lighting",
      "relation": "subtopic",
      "weight": 0.9
    },
    {
      "source": "rendering.raytracing",
      "target": "rendering.lumen",
      "relation": "related",
      "weight": 0.7
    },
    {
      "source": "character.metahuman",
      "target": "animation.control_rig",
      "relation": "related",
      "weight": 0.8
    },
    {
      "source": "animation.control_rig",
      "target": "animation.general",
      "relation": "subtopic",
      "weight": 0.85
    },
    {
      "source": "cinematic.sequencer",
      "target": "animation.general",
      "relation": "related",
      "weight": 0.7
    },
    {
      "source": "platform.quest",
      "target": "platform.vr",
      "relation": "subtopic",
      "weight": 0.95
    },
    {
      "source": "xr.openxr",
      "target": "platform.vr",
      "relation": "related",
      "weight": 0.9
    },
    {
      "source": "ui.hud",
      "target": "ui.umg",
      "relation": "subtopic",
      "weight": 0.85
    },
    {
      "source": "tool.uat",
      "target": "build.packaging",
      "relation": "related",
      "weight": 0.9
    },
    {
      "source": "tool.ubt",
      "target": "tool.uat",
      "relation": "related",
      "weight": 0.8
    },
    {
      "source": "tool.ubt",
      "target": "scripting.cpp",
      "relation": "related",
      "weight": 0.75
    },
    {
      "source": "debug.callstack",
      "target": "crash.access_violation",
      "relation": "related",
      "weight": 0.85
    },
    {
      "source": "debug.symbols",
      "target": "debug.callstack",
      "relation": "related",
      "weight": 0.9
    },
    {
      "source": "debug.output_log",
      "target": "debug.callstack",
      "relation": "related",
      "weight": 0.7
    },
    {
      "source": "template.lyra",
      "target": "genre.fps",
      "relation": "related",
      "weight": 0.85
    },
    {
      "source": "genre.platformer",
      "target": "genre.2d",
      "relation": "related",
      "weight": 0.6
    },
    {
      "source": "environment.landscape",
      "target": "environment.level_design",
      "relation": "related",
      "weight": 0.75
    },
    {
      "source": "rendering.niagara",
      "target": "rendering.material",
      "relation": "related",
      "weight": 0.65
    },
    {
      "source": "audio.metasounds",
      "target": "rendering.niagara",
      "relation": "related",
      "weight": 0.4
    },
    {
      "source": "specialty.archviz",
      "target": "rendering.lumen",
      "relation": "related",
      "weight": 0.8
    },
    {
      "source": "specialty.dmx",
      "target": "rendering.lighting",
      "relation": "related",
      "weight": 0.7
    },
    {
      "source": "multiplayer.replication",
      "target": "scripting.blueprint",
      "relation": "related",
      "weight": 0.6
    },
    {
      "source": "multiplayer.replication",
      "target": "scripting.cpp",
      "relation": "related",
      "weight": 0.7
    },
    {
      "source": "ai.behavior_tree",
      "target": "scripting.blueprint",
      "relation": "related",
      "weight": 0.75
    },
    {
      "source": "genre.rpg",
      "target": "ai.behavior_tree",
      "relation": "related",
      "weight": 0.6
    },
    {
      "source": "genre.rts",
      "target": "ai.behavior_tree",
      "relation": "related",
      "weight": 0.7
    },
    {
      "source": "rendering.niagara",
      "target": "rendering.niagara",
      "relation": "replaces",
      "target_legacy": "cascade",
      "weight": 1.0,
      "note": "Niagara replaces Cascade particle system"
    }
  ]
}
