{
  "_meta": {
    "version": "1.0.0",
    "lastUpdated": "2026-02-11",
    "legalNote": "Official Epic Games YouTube content only.",
    "totalResources": 39
  },
  "channels": {
    "epic_official": {
      "name": "Unreal Engine (Official)",
      "url": "https://www.youtube.com/@UnrealEngine",
      "vetted": true,
      "trustTier": "official"
    }
  },
  "resources": [
    {
      "id": "yt_001",
      "source": "epic_youtube",
      "channelKey": "epic_official",
      "title": "Your First Hour in Unreal Engine 5",
      "url": "https://www.youtube.com/watch?v=k-zMkzmduqI",
      "topics": [
        "foundation",
        "editor",
        "navigation"
      ],
      "tier": "beginner",
      "durationMinutes": 60,
      "ue5Version": "5.0+",
      "addedDate": "2026-02-10",
      "removable": true,
      "description": "Official Epic walkthrough of the UE5 editor interface, viewport navigation, content browser, and basic level editing. Perfect starting point for absolute beginners.",
      "keyTakeaways": [
        "Navigate the 3D viewport using WASD + right-click mouse look",
        "Use the Content Browser to import and organize assets",
        "Place actors in a level and adjust transforms (location, rotation, scale)",
        "Understand the difference between the World Outliner and Details panel"
      ],
      "chapters": [
        {
          "label": "Editor Interface Tour",
          "seconds": 0
        },
        {
          "label": "Viewport Navigation",
          "seconds": 600
        },
        {
          "label": "Content Browser & Assets",
          "seconds": 1800
        },
        {
          "label": "Placing & Transforming Actors",
          "seconds": 2700
        }
      ],
      "tag_ids": [
        "ai.navigation",
        "tools.editor",
        "topic.ue5_general"
      ]
    },
    {
      "id": "yt_002",
      "source": "epic_youtube",
      "channelKey": "epic_official",
      "title": "Unreal Engine 5 Beginner Tutorial - UE5 Starter Course",
      "url": "https://www.youtube.com/watch?v=gQmiqmxJMtA",
      "topics": [
        "foundation",
        "blueprint",
        "materials",
        "lighting"
      ],
      "tier": "beginner",
      "durationMinutes": 300,
      "ue5Version": "5.0+",
      "addedDate": "2026-02-10",
      "removable": true,
      "description": "Comprehensive beginner course covering Blueprints, materials, lighting, and level design. A full 5-hour guided project that builds a complete game environment.",
      "keyTakeaways": [
        "Create and connect Blueprint nodes for gameplay logic",
        "Build basic materials with texture samples and parameters",
        "Set up directional, point, and spot lights for a scene",
        "Combine all skills to build a playable game level from scratch"
      ],
      "chapters": [
        {
          "label": "Project Setup",
          "seconds": 0
        },
        {
          "label": "Blueprint Fundamentals",
          "seconds": 1200
        },
        {
          "label": "Materials & Textures",
          "seconds": 6000
        },
        {
          "label": "Lighting Your Scene",
          "seconds": 10800
        },
        {
          "label": "Final Level Assembly",
          "seconds": 14400
        }
      ],
      "tag_ids": [
        "rendering.lighting",
        "rendering.material",
        "scripting.blueprint",
        "topic.ue5_general"
      ]
    },
    {
      "id": "yt_003",
      "source": "epic_youtube",
      "channelKey": "epic_official",
      "title": "Building Open Worlds in Unreal Engine 5",
      "url": "https://www.youtube.com/watch?v=EEf07ggFWRw",
      "topics": [
        "world_building",
        "landscape",
        "world_partition"
      ],
      "tier": "intermediate",
      "durationMinutes": 90,
      "ue5Version": "5.0+",
      "addedDate": "2026-02-10",
      "removable": true,
      "description": "Deep dive into building large open worlds using World Partition, landscape tools, and data layers. Covers streaming, HLOD, and performance strategies for massive maps.",
      "keyTakeaways": [
        "Enable and configure World Partition for automatic level streaming",
        "Use the Landscape tool to sculpt terrain with layers and materials",
        "Set up Data Layers to organize streaming content by gameplay region",
        "Optimize open world performance with HLOD and distance culling"
      ],
      "chapters": [
        {
          "label": "World Partition Overview",
          "seconds": 0
        },
        {
          "label": "Landscape Creation",
          "seconds": 1200
        },
        {
          "label": "Streaming & Data Layers",
          "seconds": 3000
        },
        {
          "label": "Performance & HLOD",
          "seconds": 4200
        }
      ],
      "tag_ids": [
        "environment.landscape",
        "world.partition",
        "worldbuilding.environment"
      ]
    },
    {
      "id": "yt_004",
      "source": "epic_youtube",
      "channelKey": "epic_official",
      "title": "Nanite | Inside Unreal",
      "url": "https://www.youtube.com/watch?v=TMorJX3Nj6U",
      "topics": [
        "nanite",
        "rendering",
        "optimization"
      ],
      "tier": "intermediate",
      "durationMinutes": 60,
      "ue5Version": "5.0+",
      "addedDate": "2026-02-10",
      "removable": true,
      "description": "Official Inside Unreal episode covering Nanite virtualized geometry — how it works, when to use it, performance characteristics, and integration with other systems like Lumen.",
      "keyTakeaways": [
        "Understand how Nanite eliminates traditional LOD workflows",
        "Enable Nanite on Static Meshes via the mesh editor settings",
        "Know which geometry types support Nanite (and which don't — skeletal, translucent)",
        "Profile Nanite performance using stat Nanite and GPU visualizations"
      ],
      "chapters": [
        {
          "label": "What Is Nanite?",
          "seconds": 0
        },
        {
          "label": "Enabling Nanite",
          "seconds": 600
        },
        {
          "label": "Supported Geometry",
          "seconds": 1500
        },
        {
          "label": "Performance Profiling",
          "seconds": 2400
        }
      ],
      "tag_ids": [
        "optimization.general",
        "rendering.general",
        "rendering.nanite"
      ]
    },
    {
      "id": "yt_005",
      "source": "epic_youtube",
      "channelKey": "epic_official",
      "title": "Lumen | Inside Unreal",
      "url": "https://www.youtube.com/watch?v=Dc1PPYl2uxA",
      "topics": [
        "lumen",
        "lighting",
        "rendering"
      ],
      "tier": "intermediate",
      "durationMinutes": 60,
      "ue5Version": "5.0+",
      "addedDate": "2026-02-10",
      "removable": true,
      "description": "Official Inside Unreal episode on Lumen — UE5's dynamic global illumination and reflection system. Covers setup, performance tuning, and visual quality settings.",
      "keyTakeaways": [
        "Understand Lumen's software ray tracing vs hardware ray tracing modes",
        "Configure Lumen GI quality through Post Process Volume settings",
        "Set up Lumen reflections using reflection capture actors as fallbacks",
        "Tune performance by adjusting Lumen Scene Detail and Final Gather Quality"
      ],
      "chapters": [
        {
          "label": "Lumen Overview",
          "seconds": 0
        },
        {
          "label": "Global Illumination Setup",
          "seconds": 600
        },
        {
          "label": "Reflections Configuration",
          "seconds": 1800
        },
        {
          "label": "Performance Tuning",
          "seconds": 2700
        }
      ],
      "tag_ids": [
        "rendering.general",
        "rendering.lighting",
        "rendering.lumen"
      ]
    },
    {
      "id": "yt_013",
      "source": "epic_youtube",
      "channelKey": "epic_official",
      "title": "Niagara VFX - Getting Started",
      "url": "https://www.youtube.com/watch?v=04kcy-RfsoU",
      "topics": [
        "vfx",
        "niagara",
        "materials"
      ],
      "tier": "beginner",
      "durationMinutes": 45,
      "ue5Version": "5.0+",
      "addedDate": "2026-02-10",
      "removable": true,
      "description": "Official introduction to UE5's Niagara VFX system — emitters, modules, particle spawning, and creating fire/smoke/spark effects from scratch.",
      "keyTakeaways": [
        "Create a Niagara System and add Emitters for different effect layers",
        "Use Spawn Rate, Lifetime, and Initial Velocity modules to control particles",
        "Apply Curl Noise Force and Drag modules for organic motion",
        "Combine multiple emitters for complex effects (fire = flames + embers + smoke)"
      ],
      "chapters": [
        {
          "label": "Niagara System Overview",
          "seconds": 0
        },
        {
          "label": "Emitter Setup",
          "seconds": 600
        },
        {
          "label": "Module Configuration",
          "seconds": 1500
        },
        {
          "label": "Multi-Layer Effects",
          "seconds": 2100
        }
      ],
      "tag_ids": [
        "rendering.material",
        "rendering.niagara",
        "vfx.niagara"
      ]
    },
    {
      "id": "yt_014",
      "source": "epic_youtube",
      "channelKey": "epic_official",
      "title": "Animation in UE5 | Feature Highlight",
      "url": "https://www.youtube.com/watch?v=WMlV7MYxOjI",
      "topics": [
        "animation",
        "skeletal",
        "control_rig"
      ],
      "tier": "beginner",
      "durationMinutes": 30,
      "ue5Version": "5.0+",
      "addedDate": "2026-02-10",
      "removable": true,
      "description": "Official feature highlight covering UE5 animation tools — Animation Blueprints, Control Rig, IK Retargeting, and the new animation workflow improvements.",
      "keyTakeaways": [
        "Set up an Animation Blueprint with State Machines for locomotion",
        "Use Control Rig for procedural animation adjustments and IK",
        "Retarget animations between different skeletal meshes using IK Retargeter",
        "Blend animations using Blend Spaces for smooth directional movement"
      ],
      "tag_ids": [
        "animation.control_rig",
        "animation.general",
        "animation.skeletal_mesh"
      ]
    },
    {
      "id": "yt_017",
      "source": "epic_youtube",
      "channelKey": "epic_official",
      "title": "Procedural Content Generation Framework",
      "url": "https://www.youtube.com/watch?v=mJpj30GHEqE",
      "topics": [
        "world_building",
        "pcg",
        "procedural"
      ],
      "tier": "intermediate",
      "durationMinutes": 60,
      "ue5Version": "5.2+",
      "addedDate": "2026-02-10",
      "removable": true,
      "description": "Official deep dive into UE5.2's Procedural Content Generation (PCG) framework — rules, data layers, point sampling, and generating landscapes procedurally.",
      "keyTakeaways": [
        "Create a PCG Graph with Point Samplers and Surface Projectors",
        "Use filters and density modifiers to control asset placement",
        "Set up exclusion volumes and bias rules for natural-looking distribution",
        "Combine PCG with landscape layers for context-aware procedural placement"
      ],
      "chapters": [
        {
          "label": "PCG Framework Concepts",
          "seconds": 0
        },
        {
          "label": "PCG Graph Editor",
          "seconds": 900
        },
        {
          "label": "Point Sampling & Filters",
          "seconds": 1800
        },
        {
          "label": "Integration with Landscape",
          "seconds": 2700
        }
      ],
      "tag_ids": [
        "environment.pcg",
        "procedural.pcg",
        "worldbuilding.environment"
      ]
    },
    {
      "id": "yt_018",
      "source": "epic_youtube",
      "channelKey": "epic_official",
      "title": "MetaSounds in Unreal Engine",
      "url": "https://www.youtube.com/watch?v=wLkSz1V19Xs",
      "topics": [
        "audio",
        "metasound"
      ],
      "tier": "intermediate",
      "durationMinutes": 45,
      "ue5Version": "5.0+",
      "addedDate": "2026-02-10",
      "removable": true,
      "description": "Introduction to MetaSounds — UE5's node-based audio system for procedural sound design, music, and real-time audio synthesis.",
      "keyTakeaways": [
        "Create a MetaSound Source and build audio graphs with oscillators",
        "Use Trigger and Envelope nodes for event-driven sound playback",
        "Connect gameplay parameters to MetaSound inputs for reactive audio",
        "Replace legacy SoundCue workflows with MetaSounds for better performance"
      ],
      "chapters": [
        {
          "label": "MetaSounds Overview",
          "seconds": 0
        },
        {
          "label": "Audio Graph Basics",
          "seconds": 600
        },
        {
          "label": "Gameplay Integration",
          "seconds": 1500
        },
        {
          "label": "Advanced Synthesis",
          "seconds": 2400
        }
      ],
      "tag_ids": [
        "audio.general",
        "audio.metasounds"
      ]
    },
    {
      "id": "yt_020",
      "source": "epic_youtube",
      "channelKey": "epic_official",
      "title": "Chaos Physics System Overview",
      "url": "https://www.youtube.com/watch?v=z2TuGSDmC68",
      "topics": [
        "gameplay",
        "physics",
        "chaos"
      ],
      "tier": "intermediate",
      "durationMinutes": 45,
      "ue5Version": "5.0+",
      "addedDate": "2026-02-10",
      "removable": true,
      "description": "Official overview of UE5's Chaos physics system — rigid body simulation, destruction, cloth, and vehicle physics configuration.",
      "keyTakeaways": [
        "Enable Chaos physics and set up rigid body simulation on Static Meshes",
        "Create Geometry Collections for destructible objects using Fracture Mode",
        "Configure Chaos Cloth simulation on Skeletal Meshes for fabric physics",
        "Set up Chaos Vehicle movement with suspension, wheels, and engine curves"
      ],
      "chapters": [
        {
          "label": "Chaos Physics Overview",
          "seconds": 0
        },
        {
          "label": "Rigid Body & Collision",
          "seconds": 600
        },
        {
          "label": "Destruction System",
          "seconds": 1500
        },
        {
          "label": "Vehicle Physics",
          "seconds": 2400
        }
      ],
      "tag_ids": [
        "physics.chaos",
        "physics.general",
        "scripting.gameplay"
      ]
    },
    {
      "id": "yt_022",
      "source": "epic_youtube",
      "channelKey": "epic_official",
      "title": "Virtual Production with nDisplay",
      "url": "https://www.youtube.com/watch?v=bBBCpogjjS0",
      "topics": [
        "cinematics",
        "virtual_production"
      ],
      "tier": "advanced",
      "durationMinutes": 90,
      "ue5Version": "5.0+",
      "addedDate": "2026-02-10",
      "removable": true,
      "description": "Advanced virtual production workflow using nDisplay for multi-display LED wall setups, real-time compositing, and in-camera VFX with UE5.",
      "keyTakeaways": [
        "Set up an nDisplay configuration for multi-node LED wall rendering",
        "Calibrate camera tracking with LiveLink for real-time compositing",
        "Use Inner Frustum rendering for perspective-correct LED backgrounds",
        "Configure color calibration and latency compensation for on-set accuracy"
      ],
      "chapters": [
        {
          "label": "nDisplay Concepts",
          "seconds": 0
        },
        {
          "label": "LED Wall Configuration",
          "seconds": 1200
        },
        {
          "label": "Camera Tracking & LiveLink",
          "seconds": 3000
        },
        {
          "label": "Color Calibration",
          "seconds": 4500
        }
      ],
      "tag_ids": [
        "cinematic.sequencer",
        "cinematic.virtual_production"
      ]
    },
    {
      "id": "yt_025",
      "source": "epic_youtube",
      "channelKey": "epic_official",
      "title": "Introduction to Blueprints | Live Training | Unreal Engine",
      "url": "https://www.youtube.com/watch?v=EFXMW_UEDco",
      "topics": [
        "blueprint",
        "gameplay",
        "foundation"
      ],
      "tier": "beginner",
      "durationMinutes": 90,
      "ue5Version": "5.0+",
      "addedDate": "2026-02-11",
      "removable": true,
      "description": "Official live training covering Blueprint fundamentals — variables, functions, events, flow control, and building a small interactive prototype from scratch.",
      "keyTakeaways": [
        "Understand the Blueprint event graph, functions, and macros",
        "Create variables and use Get/Set nodes for state management",
        "Wire up input events and gameplay triggers with Blueprint logic",
        "Debug Blueprints using breakpoints and the watch window"
      ],
      "chapters": [
        {
          "label": "Blueprint Basics",
          "seconds": 0
        },
        {
          "label": "Variables & Functions",
          "seconds": 1200
        },
        {
          "label": "Gameplay Logic",
          "seconds": 3000
        },
        {
          "label": "Debugging Tips",
          "seconds": 4500
        }
      ],
      "tag_ids": [
        "scripting.blueprint",
        "scripting.gameplay",
        "topic.ue5_general"
      ]
    },
    {
      "id": "yt_026",
      "source": "epic_youtube",
      "channelKey": "epic_official",
      "title": "Blueprint Communications | Live Training | Unreal Engine",
      "url": "https://www.youtube.com/watch?v=EM_HYqQdToA",
      "topics": [
        "blueprint",
        "communication",
        "interfaces"
      ],
      "tier": "intermediate",
      "durationMinutes": 60,
      "ue5Version": "5.0+",
      "addedDate": "2026-02-11",
      "removable": true,
      "description": "Official training on Blueprint communication patterns — direct references, casting, Blueprint Interfaces, and Event Dispatchers for decoupled systems.",
      "keyTakeaways": [
        "Use direct Blueprint references and casting for simple communication",
        "Implement Blueprint Interfaces for decoupled cross-actor messaging",
        "Set up Event Dispatchers for observer-pattern notifications",
        "Choose the right communication pattern based on coupling needs"
      ],
      "chapters": [
        {
          "label": "Direct References",
          "seconds": 0
        },
        {
          "label": "Blueprint Interfaces",
          "seconds": 1200
        },
        {
          "label": "Event Dispatchers",
          "seconds": 2400
        },
        {
          "label": "Best Practices",
          "seconds": 3000
        }
      ],
      "tag_ids": [
        "scripting.blueprint",
        "scripting.interface"
      ]
    },
    {
      "id": "yt_027",
      "source": "epic_youtube",
      "channelKey": "epic_official",
      "title": "Enhanced Input | Inside Unreal",
      "url": "https://www.youtube.com/watch?v=bY6Nl2MFMnI",
      "topics": [
        "input",
        "enhanced_input",
        "gameplay"
      ],
      "tier": "beginner",
      "durationMinutes": 45,
      "ue5Version": "5.1+",
      "addedDate": "2026-02-11",
      "removable": true,
      "description": "Official Inside Unreal episode on UE5's Enhanced Input system — Input Actions, Input Mapping Contexts, modifiers, triggers, and runtime rebinding.",
      "keyTakeaways": [
        "Create Input Actions as data assets for movement, look, and interact",
        "Set up Input Mapping Contexts to bind actions to keys/buttons",
        "Use Modifiers (Negate, Dead Zone, Swizzle) to transform raw input",
        "Switch mapping contexts at runtime for different gameplay modes"
      ],
      "chapters": [
        {
          "label": "Enhanced Input Overview",
          "seconds": 0
        },
        {
          "label": "Input Actions Setup",
          "seconds": 600
        },
        {
          "label": "Mapping Contexts",
          "seconds": 1500
        },
        {
          "label": "Runtime Rebinding",
          "seconds": 2100
        }
      ],
      "tag_ids": [
        "scripting.gameplay"
      ]
    },
    {
      "id": "yt_028",
      "source": "epic_youtube",
      "channelKey": "epic_official",
      "title": "UMG UI in 300 Seconds | Unreal Engine",
      "url": "https://www.youtube.com/watch?v=9hpMPnETfJk",
      "topics": [
        "ui",
        "umg",
        "hud"
      ],
      "tier": "beginner",
      "durationMinutes": 5,
      "ue5Version": "5.0+",
      "addedDate": "2026-02-11",
      "removable": true,
      "description": "Fast-paced official overview of UMG — Widget Blueprints, the UMG Designer, Canvas Panel layout, and spawning/removing widgets at runtime.",
      "keyTakeaways": [
        "Create a Widget Blueprint and use the UMG Designer for layout",
        "Use Canvas Panel, Horizontal/Vertical Boxes for responsive UI",
        "Spawn widgets at runtime with Create Widget and Add to Viewport",
        "Bind UI elements to gameplay variables for dynamic HUD updates"
      ],
      "tag_ids": [
        "ui.hud",
        "ui.umg"
      ]
    },
    {
      "id": "yt_029",
      "source": "epic_youtube",
      "channelKey": "epic_official",
      "title": "Introduction to UMG | Live Training | Unreal Engine",
      "url": "https://www.youtube.com/watch?v=MHGE6lBMYOg",
      "topics": [
        "ui",
        "umg",
        "hud",
        "menus"
      ],
      "tier": "beginner",
      "durationMinutes": 60,
      "ue5Version": "5.0+",
      "addedDate": "2026-02-11",
      "removable": true,
      "description": "Official live training on building UIs with UMG — HUD creation, main menus, button styling, text binding, and input mode switching.",
      "keyTakeaways": [
        "Build a full HUD with health bars, ammo counters, and crosshairs",
        "Create main menus with button navigation and input mode switching",
        "Use bindings and animations to make UI elements feel responsive",
        "Handle focus and gamepad navigation for accessible UI"
      ],
      "chapters": [
        {
          "label": "UMG Designer Basics",
          "seconds": 0
        },
        {
          "label": "Building a HUD",
          "seconds": 900
        },
        {
          "label": "Main Menu Setup",
          "seconds": 2100
        },
        {
          "label": "Polish & Animations",
          "seconds": 3000
        }
      ],
      "tag_ids": [
        "ui.hud",
        "ui.umg"
      ]
    },
    {
      "id": "yt_030",
      "source": "epic_youtube",
      "channelKey": "epic_official",
      "title": "Sequencer 101: Triggering Gameplay | Unreal Engine 5 Cinematics",
      "url": "https://www.youtube.com/watch?v=HLjBCjVHxmk",
      "topics": [
        "cinematics",
        "sequencer",
        "gameplay"
      ],
      "tier": "intermediate",
      "durationMinutes": 30,
      "ue5Version": "5.0+",
      "addedDate": "2026-02-11",
      "removable": true,
      "description": "Official tutorial on using UE5 Sequencer to trigger gameplay events — camera cuts, event tracks, binding actors, and blending cinematic sequences with gameplay.",
      "keyTakeaways": [
        "Create Level Sequences and add camera cuts with shot tracks",
        "Use Event Tracks to fire Blueprint events at specific frames",
        "Bind possessable actors and control their properties over time",
        "Blend between cinematic cameras and gameplay cameras smoothly"
      ],
      "chapters": [
        {
          "label": "Sequencer Basics",
          "seconds": 0
        },
        {
          "label": "Camera & Shot Tracks",
          "seconds": 600
        },
        {
          "label": "Event Tracks",
          "seconds": 1200
        },
        {
          "label": "Gameplay Integration",
          "seconds": 1500
        }
      ],
      "tag_ids": [
        "cinematic.sequencer",
        "scripting.gameplay"
      ]
    },
    {
      "id": "yt_031",
      "source": "epic_youtube",
      "channelKey": "epic_official",
      "title": "Creating Cinematics with Sequencer | Inside Unreal",
      "url": "https://www.youtube.com/watch?v=GZm5rU0hIFQ",
      "topics": [
        "cinematics",
        "sequencer",
        "animation"
      ],
      "tier": "intermediate",
      "durationMinutes": 60,
      "ue5Version": "5.0+",
      "addedDate": "2026-02-11",
      "removable": true,
      "description": "Official Inside Unreal episode on cinematic production with Sequencer — multi-camera setups, skeletal animation tracks, audio sync, and Movie Render Queue.",
      "keyTakeaways": [
        "Set up multi-camera rigs with automatic switching in Sequencer",
        "Animate skeletal meshes and blend between animation clips",
        "Add audio tracks and sync sound effects to visual events",
        "Render high-quality output using Movie Render Queue with anti-aliasing"
      ],
      "chapters": [
        {
          "label": "Sequencer Overview",
          "seconds": 0
        },
        {
          "label": "Multi-Camera Setup",
          "seconds": 900
        },
        {
          "label": "Animation & Audio",
          "seconds": 2400
        },
        {
          "label": "Movie Render Queue",
          "seconds": 3000
        }
      ],
      "tag_ids": [
        "animation.general",
        "cinematic.sequencer"
      ]
    },
    {
      "id": "yt_032",
      "source": "epic_youtube",
      "channelKey": "epic_official",
      "title": "Introduction to AI with Blueprints | Live Training | Unreal Engine",
      "url": "https://www.youtube.com/watch?v=tKVWLSxBCEY",
      "topics": [
        "ai",
        "behavior_tree",
        "blueprint",
        "navigation"
      ],
      "tier": "beginner",
      "durationMinutes": 90,
      "ue5Version": "5.0+",
      "addedDate": "2026-02-11",
      "removable": true,
      "description": "Official live training covering AI fundamentals — AI Controllers, Behavior Trees, Blackboards, Nav Mesh navigation, and AI Perception for detection.",
      "keyTakeaways": [
        "Set up an AI Controller and assign it to a character Blueprint",
        "Build Behavior Trees with sequences, selectors, and tasks",
        "Use Blackboard keys to store and share AI state data",
        "Configure NavMesh Bounds Volume for AI pathfinding"
      ],
      "chapters": [
        {
          "label": "AI Controller Setup",
          "seconds": 0
        },
        {
          "label": "Behavior Trees",
          "seconds": 1200
        },
        {
          "label": "Blackboard & Tasks",
          "seconds": 3000
        },
        {
          "label": "NavMesh & Perception",
          "seconds": 4200
        }
      ],
      "tag_ids": [
        "ai.behavior_tree",
        "ai.navigation",
        "scripting.blueprint"
      ]
    },
    {
      "id": "yt_033",
      "source": "epic_youtube",
      "channelKey": "epic_official",
      "title": "AI Perception System | Inside Unreal",
      "url": "https://www.youtube.com/watch?v=Gib5MdN2VFM",
      "topics": [
        "ai",
        "perception",
        "gameplay"
      ],
      "tier": "intermediate",
      "durationMinutes": 45,
      "ue5Version": "5.0+",
      "addedDate": "2026-02-11",
      "removable": true,
      "description": "Official deep dive into UE5's AI Perception system — sight, hearing, damage senses, and integrating perception with Behavior Trees for reactive AI.",
      "keyTakeaways": [
        "Configure sight, hearing, and damage perception senses on AI",
        "Set up AI Perception Stimuli Sources on player characters",
        "React to perception events (On Target Perceived) in Behavior Trees",
        "Tune perception parameters for stealth gameplay (FOV, range, age)"
      ],
      "chapters": [
        {
          "label": "Perception Overview",
          "seconds": 0
        },
        {
          "label": "Sight & Hearing Senses",
          "seconds": 600
        },
        {
          "label": "Stimuli Sources",
          "seconds": 1500
        },
        {
          "label": "Behavior Tree Integration",
          "seconds": 2100
        }
      ],
      "tag_ids": [
        "ai.behavior_tree",
        "ai.navigation",
        "scripting.gameplay"
      ]
    },
    {
      "id": "yt_034",
      "source": "epic_youtube",
      "channelKey": "epic_official",
      "title": "Introduction to Materials | Live Training | Unreal Engine",
      "url": "https://www.youtube.com/watch?v=lngF4VVNER4",
      "topics": [
        "materials",
        "rendering",
        "textures"
      ],
      "tier": "beginner",
      "durationMinutes": 60,
      "ue5Version": "5.0+",
      "addedDate": "2026-02-11",
      "removable": true,
      "description": "Official training on UE5 Material Editor — PBR workflow, texture sampling, material parameters, instances, and building common material types (metal, glass, fabric).",
      "keyTakeaways": [
        "Understand PBR material inputs: Base Color, Metallic, Roughness, Normal",
        "Create Material Instances for efficient parameter tweaking without recompiling",
        "Use Texture Sample nodes and coordinate manipulation for tiling/UV effects",
        "Build dynamic materials with Material Parameter Collections for runtime changes"
      ],
      "chapters": [
        {
          "label": "Material Editor Tour",
          "seconds": 0
        },
        {
          "label": "PBR Workflow",
          "seconds": 900
        },
        {
          "label": "Material Instances",
          "seconds": 2400
        },
        {
          "label": "Dynamic Materials",
          "seconds": 3000
        }
      ],
      "tag_ids": [
        "rendering.general",
        "rendering.material",
        "rendering.texture"
      ]
    },
    {
      "id": "yt_035",
      "source": "epic_youtube",
      "channelKey": "epic_official",
      "title": "Substance & Quixel Integration | Inside Unreal",
      "url": "https://www.youtube.com/watch?v=u9PECqXce8A",
      "topics": [
        "materials",
        "quixel",
        "megascans",
        "textures"
      ],
      "tier": "intermediate",
      "durationMinutes": 45,
      "ue5Version": "5.0+",
      "addedDate": "2026-02-11",
      "removable": true,
      "description": "Official overview of using Quixel Bridge and Megascans within UE5 — importing photogrammetry assets, setting up Nanite meshes, and applying scanned materials.",
      "keyTakeaways": [
        "Use Quixel Bridge (built into UE5) to browse and import Megascans assets",
        "Auto-enable Nanite on imported Megascans meshes for unlimited detail",
        "Apply scanned surface materials and customize them with blend layers",
        "Organize large asset libraries with naming conventions and folder structure"
      ],
      "chapters": [
        {
          "label": "Quixel Bridge Overview",
          "seconds": 0
        },
        {
          "label": "Importing Assets",
          "seconds": 600
        },
        {
          "label": "Nanite Integration",
          "seconds": 1500
        },
        {
          "label": "Material Customization",
          "seconds": 2100
        }
      ],
      "tag_ids": [
        "asset.fab",
        "rendering.material",
        "rendering.texture"
      ]
    },
    {
      "id": "yt_036",
      "source": "epic_youtube",
      "channelKey": "epic_official",
      "title": "Introduction to C++ Programming | Live Training | Unreal Engine",
      "url": "https://www.youtube.com/watch?v=MmJMC7tbMfc",
      "topics": [
        "cpp",
        "programming",
        "foundation"
      ],
      "tier": "intermediate",
      "durationMinutes": 90,
      "ue5Version": "5.0+",
      "addedDate": "2026-02-11",
      "removable": true,
      "description": "Official live training on C++ for Unreal — project setup, AActor, UObject, UPROPERTY/UFUNCTION macros, and how C++ and Blueprints work together.",
      "keyTakeaways": [
        "Set up a C++ project and understand the Unreal build system (UBT)",
        "Create C++ classes inheriting from AActor and ACharacter",
        "Expose C++ properties to Blueprints with UPROPERTY and UFUNCTION",
        "Understand the relationship between C++ base classes and Blueprint children"
      ],
      "chapters": [
        {
          "label": "Project Setup",
          "seconds": 0
        },
        {
          "label": "AActor & UObject",
          "seconds": 1200
        },
        {
          "label": "UPROPERTY & UFUNCTION",
          "seconds": 3000
        },
        {
          "label": "C++ ↔ Blueprint Workflow",
          "seconds": 4200
        }
      ],
      "tag_ids": [
        "scripting.cpp",
        "topic.ue5_general"
      ]
    },
    {
      "id": "yt_037",
      "source": "epic_youtube",
      "channelKey": "epic_official",
      "title": "Networking & Multiplayer | Inside Unreal",
      "url": "https://www.youtube.com/watch?v=JOJP0CvpB8w",
      "topics": [
        "multiplayer",
        "networking",
        "replication"
      ],
      "tier": "advanced",
      "durationMinutes": 60,
      "ue5Version": "5.0+",
      "addedDate": "2026-02-11",
      "removable": true,
      "description": "Official Inside Unreal episode on UE5 networking — server-client model, replication, RPCs, relevancy, and testing multiplayer locally with multiple sessions.",
      "keyTakeaways": [
        "Understand UE5's authoritative server model and client prediction",
        "Mark variables as Replicated with DOREPLIFETIME for state sync",
        "Implement Server, Client, and Multicast RPCs for remote function calls",
        "Test multiplayer locally using the Play-In-Editor net mode settings"
      ],
      "chapters": [
        {
          "label": "Server-Client Architecture",
          "seconds": 0
        },
        {
          "label": "Replication Setup",
          "seconds": 900
        },
        {
          "label": "RPCs & Ownership",
          "seconds": 2100
        },
        {
          "label": "Local Testing",
          "seconds": 3000
        }
      ],
      "tag_ids": [
        "networking.general",
        "networking.multiplayer",
        "networking.replication"
      ]
    },
    {
      "id": "yt_038",
      "source": "epic_youtube",
      "channelKey": "epic_official",
      "title": "Collision & Physics Interaction | Live Training | Unreal Engine",
      "url": "https://www.youtube.com/watch?v=YRbr6FKEzR8",
      "topics": [
        "collision",
        "physics",
        "gameplay"
      ],
      "tier": "beginner",
      "durationMinutes": 60,
      "ue5Version": "5.0+",
      "addedDate": "2026-02-11",
      "removable": true,
      "description": "Official training on collision setup — collision channels, presets, object responses, overlap vs block events, and line/sphere trace usage.",
      "keyTakeaways": [
        "Understand collision channels (WorldStatic, WorldDynamic, Pawn, etc.)",
        "Configure collision presets for blocking, overlapping, and ignoring",
        "Use On Component Begin Overlap events for trigger volumes",
        "Perform line traces and sphere traces for raycast-based interaction"
      ],
      "chapters": [
        {
          "label": "Collision Overview",
          "seconds": 0
        },
        {
          "label": "Channels & Presets",
          "seconds": 700
        },
        {
          "label": "Overlap Events",
          "seconds": 1800
        },
        {
          "label": "Line Traces",
          "seconds": 2700
        }
      ],
      "tag_ids": [
        "physics.collision",
        "physics.general",
        "scripting.gameplay"
      ]
    },
    {
      "id": "yt_039",
      "source": "epic_youtube",
      "channelKey": "epic_official",
      "title": "Character Movement Component | Inside Unreal",
      "url": "https://www.youtube.com/watch?v=fPgxVYnI4Uc",
      "topics": [
        "character_movement",
        "gameplay",
        "physics"
      ],
      "tier": "intermediate",
      "durationMinutes": 45,
      "ue5Version": "5.0+",
      "addedDate": "2026-02-11",
      "removable": true,
      "description": "Official deep dive into UE5's Character Movement Component — movement modes (walk, fly, swim), acceleration, braking, and customizing character physics.",
      "keyTakeaways": [
        "Configure walking, jumping, flying, and swimming movement modes",
        "Tune Max Walk Speed, Acceleration, and Braking Deceleration for game feel",
        "Implement custom movement modes for mechanics like wall-running",
        "Handle networked character movement with prediction and correction"
      ],
      "chapters": [
        {
          "label": "CMC Overview",
          "seconds": 0
        },
        {
          "label": "Movement Modes",
          "seconds": 600
        },
        {
          "label": "Tuning Game Feel",
          "seconds": 1500
        },
        {
          "label": "Custom Modes",
          "seconds": 2100
        }
      ],
      "tag_ids": [
        "character.general",
        "physics.general",
        "scripting.gameplay"
      ]
    },
    {
      "id": "yt_040",
      "source": "epic_youtube",
      "channelKey": "epic_official",
      "title": "Packaging Your Project | Unreal Engine",
      "url": "https://www.youtube.com/watch?v=hHR-HRj2mhI",
      "topics": [
        "packaging",
        "deployment",
        "optimization"
      ],
      "tier": "beginner",
      "durationMinutes": 20,
      "ue5Version": "5.0+",
      "addedDate": "2026-02-11",
      "removable": true,
      "description": "Official tutorial on packaging your UE5 game — build configurations, project settings for default map, cooking content, and creating distributable builds.",
      "keyTakeaways": [
        "Set the default Game Map and Game Mode in Project Settings before packaging",
        "Choose Development vs Shipping build configuration based on your needs",
        "Package for Windows/Mac/Linux using File → Package Project",
        "Troubleshoot common packaging errors (missing modules, cook failures)"
      ],
      "chapters": [
        {
          "label": "Pre-Package Settings",
          "seconds": 0
        },
        {
          "label": "Build Configurations",
          "seconds": 300
        },
        {
          "label": "Packaging Process",
          "seconds": 600
        },
        {
          "label": "Troubleshooting",
          "seconds": 900
        }
      ],
      "tag_ids": [
        "build.packaging",
        "optimization.general"
      ]
    },
    {
      "id": "yt_041",
      "source": "epic_youtube",
      "channelKey": "epic_official",
      "title": "Level Design Workflow | Inside Unreal",
      "url": "https://www.youtube.com/watch?v=69bYnflGhZI",
      "topics": [
        "level_design",
        "world_building",
        "blockout"
      ],
      "tier": "beginner",
      "durationMinutes": 60,
      "ue5Version": "5.0+",
      "addedDate": "2026-02-11",
      "removable": true,
      "description": "Official workflow guide for level design in UE5 — BSP blockout, modular kit-bashing, lighting passes, and iterative design from greybox to final art.",
      "keyTakeaways": [
        "Use BSP brushes and modeling tools for rapid greybox prototyping",
        "Apply modular meshes with grid snapping for clean kit-bash levels",
        "Iterate through layout, lighting, and detail passes for polish",
        "Playtest early and often using PIE to validate spatial flow"
      ],
      "chapters": [
        {
          "label": "Greybox Blockout",
          "seconds": 0
        },
        {
          "label": "Modular Kit-Bashing",
          "seconds": 1200
        },
        {
          "label": "Lighting Pass",
          "seconds": 2400
        },
        {
          "label": "Detail & Polish",
          "seconds": 3000
        }
      ],
      "tag_ids": [
        "environment.level_design",
        "world.level_design",
        "worldbuilding.environment"
      ]
    },
    {
      "id": "yt_042",
      "source": "epic_youtube",
      "channelKey": "epic_official",
      "title": "Gameplay Ability System | Inside Unreal",
      "url": "https://www.youtube.com/watch?v=LXRd-v7yXIQ",
      "topics": [
        "gas",
        "gameplay_ability",
        "gameplay"
      ],
      "tier": "advanced",
      "durationMinutes": 60,
      "ue5Version": "5.0+",
      "addedDate": "2026-02-11",
      "removable": true,
      "description": "Official overview of the Gameplay Ability System (GAS) — Ability System Components, Gameplay Abilities, Gameplay Effects, Gameplay Tags, and Attribute Sets.",
      "keyTakeaways": [
        "Set up Ability System Component and Attribute Sets on characters",
        "Create Gameplay Abilities with activation, cooldown, and cost logic",
        "Use Gameplay Effects to modify attributes (damage, healing, buffs)",
        "Organize game state with Gameplay Tags for clean condition checking"
      ],
      "chapters": [
        {
          "label": "GAS Architecture",
          "seconds": 0
        },
        {
          "label": "Abilities & Activation",
          "seconds": 900
        },
        {
          "label": "Effects & Attributes",
          "seconds": 2100
        },
        {
          "label": "Gameplay Tags",
          "seconds": 3000
        }
      ],
      "tag_ids": [
        "scripting.gameplay",
        "scripting.gameplay_tags"
      ]
    },
    {
      "id": "yt_043",
      "source": "epic_youtube",
      "channelKey": "epic_official",
      "title": "Data-Driven Design with Data Tables | Live Training | Unreal Engine",
      "url": "https://www.youtube.com/watch?v=xaJoIEBv3dE",
      "topics": [
        "data_tables",
        "data_driven",
        "blueprint"
      ],
      "tier": "intermediate",
      "durationMinutes": 45,
      "ue5Version": "5.0+",
      "addedDate": "2026-02-11",
      "removable": true,
      "description": "Official training on data-driven game design — Data Tables, Struct-based rows, CSV import/export, and runtime lookup for items, weapons, and abilities.",
      "keyTakeaways": [
        "Create Structs and Data Tables for game entities (items, stats, abilities)",
        "Import/export Data Tables from CSV for external editing",
        "Look up Data Table rows at runtime from Blueprint and C++",
        "Use Soft Object References in Data Tables for deferred asset loading"
      ],
      "chapters": [
        {
          "label": "Structs & Data Tables",
          "seconds": 0
        },
        {
          "label": "CSV Workflow",
          "seconds": 900
        },
        {
          "label": "Runtime Lookups",
          "seconds": 1800
        },
        {
          "label": "Soft References",
          "seconds": 2400
        }
      ],
      "tag_ids": [
        "scripting.blueprint",
        "scripting.struct"
      ]
    },
    {
      "id": "yt_044",
      "source": "epic_youtube",
      "channelKey": "epic_official",
      "title": "Post Process Effects | Inside Unreal",
      "url": "https://www.youtube.com/watch?v=v9bV9bZ5fvE",
      "topics": [
        "post_process",
        "rendering",
        "visual_effects"
      ],
      "tier": "intermediate",
      "durationMinutes": 45,
      "ue5Version": "5.0+",
      "addedDate": "2026-02-11",
      "removable": true,
      "description": "Official guide to UE5 Post Process Volumes — bloom, color grading, depth of field, exposure, and building stylized visual looks.",
      "keyTakeaways": [
        "Set up Post Process Volumes with Infinite Extent for global effects",
        "Configure bloom, lens flares, and chromatic aberration for cinematic looks",
        "Use LUT-based color grading to establish a visual tone",
        "Control exposure with auto-exposure settings or manual EV100"
      ],
      "chapters": [
        {
          "label": "Post Process Volume Setup",
          "seconds": 0
        },
        {
          "label": "Bloom & Lens Effects",
          "seconds": 600
        },
        {
          "label": "Color Grading & LUTs",
          "seconds": 1500
        },
        {
          "label": "Exposure Control",
          "seconds": 2400
        }
      ],
      "tag_ids": [
        "rendering.general",
        "rendering.postprocess",
        "vfx.niagara"
      ]
    },
    {
      "id": "yt_045",
      "source": "epic_youtube",
      "channelKey": "epic_official",
      "title": "Foliage & Vegetation in UE5 | Feature Highlight",
      "url": "https://www.youtube.com/watch?v=Y78pV0_ZnIA",
      "topics": [
        "foliage",
        "landscape",
        "world_building",
        "nanite"
      ],
      "tier": "intermediate",
      "durationMinutes": 30,
      "ue5Version": "5.0+",
      "addedDate": "2026-02-11",
      "removable": true,
      "description": "Official feature highlight on UE5 foliage tools — paint mode, procedural placement, Nanite foliage support, and wind interaction setup.",
      "keyTakeaways": [
        "Use the Foliage Paint tool for manual vegetation placement",
        "Configure density, scale randomization, and ground slope alignment",
        "Enable Nanite on foliage meshes for massive polygon counts without LOD",
        "Set up Simple Grass Wind material for natural foliage animation"
      ],
      "tag_ids": [
        "environment.foliage",
        "environment.landscape",
        "rendering.nanite",
        "worldbuilding.environment"
      ]
    },
    {
      "id": "yt_046",
      "source": "epic_youtube",
      "channelKey": "epic_official",
      "title": "Mass Entity Framework | Unreal Fest 2023",
      "url": "https://www.youtube.com/watch?v=f9q8A-9DRgM",
      "topics": [
        "mass_entity",
        "ecs",
        "optimization",
        "gameplay"
      ],
      "tier": "advanced",
      "durationMinutes": 45,
      "ue5Version": "5.2+",
      "addedDate": "2026-02-11",
      "removable": true,
      "description": "Official Unreal Fest talk on the Mass Entity framework — Entity Component System architecture for thousands of entities, processors, traits, and integration with SmartObjects.",
      "keyTakeaways": [
        "Understand the Mass Entity ECS architecture (Entities, Fragments, Processors)",
        "Create Mass Entity Configs with Traits for bulk spawning",
        "Write custom Processors for simulation logic (movement, avoidance)",
        "Integrate Mass Entity with SmartObjects for crowd behavior"
      ],
      "chapters": [
        {
          "label": "ECS Architecture",
          "seconds": 0
        },
        {
          "label": "Traits & Fragments",
          "seconds": 900
        },
        {
          "label": "Custom Processors",
          "seconds": 1800
        },
        {
          "label": "SmartObjects Integration",
          "seconds": 2700
        }
      ],
      "tag_ids": [
        "optimization.general",
        "scripting.gameplay"
      ]
    },
    {
      "id": "yt_047",
      "source": "epic_youtube",
      "channelKey": "epic_official",
      "title": "Building AI with State Trees | Unreal Fest",
      "url": "https://www.youtube.com/watch?v=3qnVCdnUYoc",
      "topics": [
        "ai",
        "state_tree",
        "gameplay"
      ],
      "tier": "advanced",
      "durationMinutes": 45,
      "ue5Version": "5.2+",
      "addedDate": "2026-02-11",
      "removable": true,
      "description": "Official Unreal Fest session on State Trees — UE5's next-gen AI behavior framework. Covers State Tree architecture, tasks, conditions, and comparison with Behavior Trees.",
      "keyTakeaways": [
        "Understand State Trees as a modern alternative to Behavior Trees",
        "Create States with Enter Conditions and linked Tasks for modular AI",
        "Use Gameplay Tag conditions for scalable state transitions",
        "Combine State Trees with SmartObjects for context-aware AI behavior"
      ],
      "chapters": [
        {
          "label": "State Tree vs Behavior Tree",
          "seconds": 0
        },
        {
          "label": "States & Tasks",
          "seconds": 600
        },
        {
          "label": "Conditions & Transitions",
          "seconds": 1500
        },
        {
          "label": "SmartObjects Integration",
          "seconds": 2400
        }
      ],
      "tag_ids": [
        "ai.behavior_tree",
        "ai.navigation",
        "scripting.gameplay"
      ]
    },
    {
      "id": "yt_048",
      "source": "epic_youtube",
      "channelKey": "epic_official",
      "title": "Landscape Sculpting & Painting | Live Training | Unreal Engine",
      "url": "https://www.youtube.com/watch?v=4yx3FCoYrsU",
      "topics": [
        "landscape",
        "terrain",
        "world_building",
        "materials"
      ],
      "tier": "beginner",
      "durationMinutes": 60,
      "ue5Version": "5.0+",
      "addedDate": "2026-02-11",
      "removable": true,
      "description": "Official training on UE5 landscape tools — creating landscapes, sculpting terrain, painting multiple material layers, and importing heightmaps.",
      "keyTakeaways": [
        "Create a Landscape with configurable section size and resolution",
        "Use sculpt, smooth, flatten, and erosion tools for terrain shaping",
        "Paint multiple landscape material layers (grass, dirt, rock) with auto-blending",
        "Import external heightmaps (16-bit PNG) for real-world terrain"
      ],
      "chapters": [
        {
          "label": "Landscape Creation",
          "seconds": 0
        },
        {
          "label": "Sculpting Tools",
          "seconds": 900
        },
        {
          "label": "Material Layers",
          "seconds": 2400
        },
        {
          "label": "Heightmap Import",
          "seconds": 3000
        }
      ],
      "tag_ids": [
        "environment.landscape",
        "rendering.material",
        "worldbuilding.environment"
      ]
    },
    {
      "id": "yt_049",
      "source": "epic_youtube",
      "channelKey": "epic_official",
      "title": "Water System Overview | Inside Unreal",
      "url": "https://www.youtube.com/watch?v=m6cCHXoHnVs",
      "topics": [
        "water",
        "world_building",
        "rendering"
      ],
      "tier": "intermediate",
      "durationMinutes": 30,
      "ue5Version": "5.0+",
      "addedDate": "2026-02-11",
      "removable": true,
      "description": "Official overview of UE5's Water System plugin — oceans, rivers, lakes, water body editing, buoyancy, and underwater post-processing.",
      "keyTakeaways": [
        "Enable the Water plugin and place Water Body actors (Ocean, River, Lake)",
        "Edit water splines and wave parameters for natural-looking water",
        "Set up buoyancy components for floating objects and swimming characters",
        "Configure underwater post-processing effects and fog"
      ],
      "chapters": [
        {
          "label": "Water Plugin Setup",
          "seconds": 0
        },
        {
          "label": "Water Body Types",
          "seconds": 400
        },
        {
          "label": "Buoyancy & Swimming",
          "seconds": 1200
        },
        {
          "label": "Underwater Effects",
          "seconds": 1600
        }
      ],
      "tag_ids": [
        "environment.water",
        "rendering.general",
        "worldbuilding.environment"
      ]
    },
    {
      "id": "yt_050",
      "source": "epic_youtube",
      "channelKey": "epic_official",
      "title": "Virtual Shadow Maps | Inside Unreal",
      "url": "https://www.youtube.com/watch?v=B7gWRb75JYo",
      "topics": [
        "shadows",
        "rendering",
        "lighting",
        "optimization"
      ],
      "tier": "intermediate",
      "durationMinutes": 30,
      "ue5Version": "5.0+",
      "addedDate": "2026-02-11",
      "removable": true,
      "description": "Official deep dive into Virtual Shadow Maps — how VSM replaces traditional cascaded shadow maps, performance tuning, and interaction with Nanite.",
      "keyTakeaways": [
        "Understand how Virtual Shadow Maps provide pixel-accurate shadows",
        "Configure VSM settings: page pool size, cache invalidation, and distance",
        "Know how VSM automatically leverages Nanite geometry for shadow rendering",
        "Profile and tune VSM performance with stat Shadow and GPU timings"
      ],
      "chapters": [
        {
          "label": "VSM Overview",
          "seconds": 0
        },
        {
          "label": "Configuration",
          "seconds": 500
        },
        {
          "label": "Nanite Integration",
          "seconds": 1200
        },
        {
          "label": "Performance Tuning",
          "seconds": 1600
        }
      ],
      "tag_ids": [
        "optimization.general",
        "rendering.general",
        "rendering.lighting",
        "rendering.vsm"
      ]
    },
    {
      "id": "yt_051",
      "source": "epic_youtube",
      "channelKey": "epic_official",
      "title": "Gameplay Mechanics with Blueprints | Live Training | Unreal Engine",
      "url": "https://www.youtube.com/watch?v=l9NX06mvp2E",
      "topics": [
        "blueprint",
        "gameplay",
        "interaction"
      ],
      "tier": "beginner",
      "durationMinutes": 90,
      "ue5Version": "5.0+",
      "addedDate": "2026-02-11",
      "removable": true,
      "description": "Official live training on building gameplay mechanics — doors, switches, pickups, health systems, and spawning with Blueprint. Complete hands-on project.",
      "keyTakeaways": [
        "Build interactive doors and switches with overlap triggers",
        "Create pickup items with Blueprint interfaces for modularity",
        "Implement a basic health and damage system using variables and events",
        "Spawn actors at runtime and control their lifecycle"
      ],
      "chapters": [
        {
          "label": "Interactive Objects",
          "seconds": 0
        },
        {
          "label": "Pickup System",
          "seconds": 1800
        },
        {
          "label": "Health & Damage",
          "seconds": 3600
        },
        {
          "label": "Spawning & Lifecycle",
          "seconds": 4800
        }
      ],
      "tag_ids": [
        "scripting.blueprint",
        "scripting.gameplay"
      ]
    },
    {
      "id": "yt_052",
      "source": "epic_youtube",
      "channelKey": "epic_official",
      "title": "Modeling Tools in UE5 | Feature Highlight",
      "url": "https://www.youtube.com/watch?v=3N_KpJWMFMI",
      "topics": [
        "modeling",
        "editor",
        "mesh_editing"
      ],
      "tier": "intermediate",
      "durationMinutes": 25,
      "ue5Version": "5.0+",
      "addedDate": "2026-02-11",
      "removable": true,
      "description": "Official feature highlight of UE5's built-in Modeling Mode — PolyEdit, mesh booleans, UV tools, and creating game-ready meshes without leaving the editor.",
      "keyTakeaways": [
        "Enter Modeling Mode and use PolyEdit for vertex/edge/face editing",
        "Use boolean operations (union, subtract, intersect) to combine meshes",
        "Generate and edit UVs with the built-in UV editor tools",
        "Export edited meshes as static mesh assets for your project"
      ],
      "chapters": [
        {
          "label": "Modeling Mode Overview",
          "seconds": 0
        },
        {
          "label": "PolyEdit Tools",
          "seconds": 400
        },
        {
          "label": "Boolean Operations",
          "seconds": 900
        },
        {
          "label": "UV Editing",
          "seconds": 1200
        }
      ],
      "tag_ids": [
        "rendering.mesh",
        "tools.editor"
      ]
    }
  ]
}
